light_cache/__init__.py
light_cache/backends/__init__.py
light_cache/backends/layered.py
light_cache/backends/memory.py
light_cache/backends/redis.py
light_cache/config/__init__.py
light_cache/config/settings.py
light_cache/core/__init__.py
light_cache/core/decorators.py
light_cache/core/exceptions.py
light_cache/core/interfaces.py
light_cache/core/key_builder.py
light_cache/core/serializers.py
light_cache/utils/__init__.py
light_cache/utils/locks.py
light_cache/utils/metrics.py
light_cache/utils/time.py
light_cache_async-0.1.0.dist-info/licenses/LICENSE
light_cache_async-0.1.0.dist-info/METADATA
light_cache_async-0.1.0.dist-info/WHEEL
light_cache_async-0.1.0.dist-info/top_level.txt
light_cache_async-0.1.0.dist-info/RECORD
