Metadata-Version: 2.4
Name: light-cache-async
Version: 0.1.0
Summary: Async caching library with Redis, Memory, L1/L2, AutoSerializer (orjson/msgspec)
Author-email: Tiago Ventura <tiago.barbano@gmail.com>
License-Expression: MIT
Project-URL: Homepage, https://github.com/tiagoBarbano/light-cache
Project-URL: Repository, https://github.com/tiagoBarbano/light-cache
Requires-Python: >=3.13
License-File: LICENSE
Requires-Dist: msgspec>=0.20.0
Requires-Dist: orjson>=3.11.5
Requires-Dist: redis>=7.1.0
Requires-Dist: twine>=6.2.0
Dynamic: license-file
